mmemoji/__init__.py
mmemoji/__main__.py
mmemoji/cli.py
mmemoji/decorators.py
mmemoji/emoji.py
mmemoji/exceptions.py
mmemoji/commands/__init__.py
mmemoji/commands/create.py
mmemoji/commands/delete.py
mmemoji/commands/download.py
mmemoji/commands/list.py
mmemoji/commands/search.py
mmemoji-0.6.0.dist-info/METADATA
mmemoji-0.6.0.dist-info/WHEEL
mmemoji-0.6.0.dist-info/entry_points.txt
mmemoji-0.6.0.dist-info/licenses/LICENSE
mmemoji-0.6.0.dist-info/RECORD
