Metadata-Version: 2.3
Name: mmemoji
Version: 0.6.0
Summary: Custom Emoji manager command-line for Mattermost 😎
Project-URL: repository, https://github.com/maxbrunet/mmemoji.git
Project-URL: changelog, https://github.com/maxbrunet/mmemoji/blob/main/CHANGELOG.md
License: GPLv3
License-File: LICENSE
Keywords: cli,emoji,mattermost
Classifier: Environment :: Web Environment
Classifier: Intended Audience :: End Users/Desktop
Classifier: License :: OSI Approved :: GNU General Public License v3 (GPLv3)
Classifier: Natural Language :: English
Classifier: Operating System :: OS Independent
Classifier: Programming Language :: Python
Classifier: Programming Language :: Python :: 3
Classifier: Programming Language :: Python :: 3.9
Classifier: Programming Language :: Python :: 3.10
Classifier: Programming Language :: Python :: 3.11
Classifier: Programming Language :: Python :: 3.12
Classifier: Programming Language :: Python :: 3.13
Classifier: Topic :: Utilities
Requires-Python: <4.0,>=3.9
Requires-Dist: click>=8.0.0
Requires-Dist: filetype>=0.1.3
Requires-Dist: mattermostdriver>=6.1.2
Requires-Dist: requests>=2.19.0
Requires-Dist: tabulate>=0.7.3
Requires-Dist: typing-extensions>=3.10.0.0; python_version < '3.10'
Requires-Dist: unidecode>=0.04.1
